django_plugin_django_header/__init__.py
django_plugin_django_header/middleware.py
django_plugin_django_header-0.1.1.dist-info/LICENSE
django_plugin_django_header-0.1.1.dist-info/METADATA
django_plugin_django_header-0.1.1.dist-info/WHEEL
django_plugin_django_header-0.1.1.dist-info/entry_points.txt
django_plugin_django_header-0.1.1.dist-info/top_level.txt
django_plugin_django_header-0.1.1.dist-info/RECORD
