Metadata-Version: 2.1
Name: django-plugin-django-header
Version: 0.1.1
Summary: Add a Django-Compositions HTTP header to a Django app
Author: Simon Willison
License: Apache-2.0
Project-URL: Homepage, https://github.com/simonw/django-plugin-django-header
Project-URL: Changelog, https://github.com/simonw/django-plugin-django-header/releases
Project-URL: Issues, https://github.com/simonw/django-plugin-django-header/issues
Project-URL: CI, https://github.com/simonw/django-plugin-django-header/actions
Classifier: License :: OSI Approved :: Apache Software License
License-File: LICENSE
Requires-Dist: django
Requires-Dist: djp
Provides-Extra: test
Requires-Dist: pytest ; extra == 'test'
Requires-Dist: pytest-django ; extra == 'test'
